napalm/__init__.py
napalm/analysis/__init__.py
napalm/analysis/ai_false_positive.py
napalm/analysis/duplicate.py
napalm/analysis/filter.py
napalm/cli/__init__.py
napalm/cli/base/__init__.py
napalm/cli/base/auto.py
napalm/cli/base/collection.py
napalm/cli/base/main.py
napalm/cli/base/run.py
napalm/cli/base/twin.py
napalm/cli/base/workflow.py
napalm/cli/dev/__init__.py
napalm/cli/dev/cli.py
napalm/cli/dev/compete.py
napalm/cli/dev/compete_model.py
napalm/cli/dev/info.py
napalm/cli/dev/init/__init__.py
napalm/cli/dev/init/main.py
napalm/cli/dev/init/python_plugin_installer.py
napalm/cli/dev/install.py
napalm/cli/dev/testing.py
napalm/package/__init__.py
napalm/package/collection.py
napalm/package/collection_manager.py
napalm/package/detector_info.py
napalm/package/discovery.py
napalm/package/entry_point.py
napalm/plugins/__init__.py
napalm/plugins/base.py
napalm/plugins/installed.py
napalm/report/__init__.py
napalm/report/fancy.py
napalm/report/markdown_report.py
napalm/report/sarif_report.py
napalm/report/simple_report.py
napalm/sarif/__init__.py
napalm/sarif/get.py
napalm/sarif/location.py
napalm/storage/__init__.py
napalm/storage/collection.py
napalm/storage/config.py
napalm/storage/pickledb_provider.py
napalm/storage/provider.py
napalm/storage/twin.py
napalm/storage/workflow.py
napalm/tool/__init__.py
napalm/tool/run.py
napalm/tool/semgrep_info.py
napalm/tool/semgrep_tool_runner.py
napalm/tool/tool_runner.py
napalm/utils/__init__.py
napalm/utils/config.py
napalm/utils/sarif.py
napalm/utils/templates.py
napalm/utils/workflow.py
templates/init/.gitignore
templates/init/README.md
templates/init/example_semgrep_rule.yml
templates/init/napalm.py.jinja2
templates/init/pyproject.toml.jinja2
templates/install/pyproject.toml.jinja2
templates/report/simple_report.md.jinja2
napalm_toolbox-0.1.5.dist-info/LICENSE
napalm_toolbox-0.1.5.dist-info/METADATA
napalm_toolbox-0.1.5.dist-info/WHEEL
napalm_toolbox-0.1.5.dist-info/entry_points.txt
napalm_toolbox-0.1.5.dist-info/RECORD
