Metadata-Version: 2.1
Name: napalm-toolbox
Version: 0.1.5
Summary: A tool to make working with security analysis tools a breeze
License: Apache-2.0
Author: JoranHonig
Author-email: JoranHonig@users.noreply.github.com
Requires-Python: >=3.12,<4.0
Classifier: License :: OSI Approved :: Apache Software License
Classifier: Programming Language :: Python :: 3
Classifier: Programming Language :: Python :: 3.12
Provides-Extra: slither
Requires-Dist: click (>=8.1.6,<9.0.0)
Requires-Dist: gitpython (>=3.1.32,<4.0.0)
Requires-Dist: importlib-metadata (>=7.0.0,<8.0.0)
Requires-Dist: jinja2 (>=3.1.2,<4.0.0)
Requires-Dist: langchain (>=0.0.352,<0.0.353)
Requires-Dist: loguru (>=0.7.0,<0.8.0)
Requires-Dist: napalm_slither (>=0.1.0,<0.2.0) ; extra == "slither"
Requires-Dist: openai (>=1.6.1,<2.0.0)
Requires-Dist: pickledb (>=0.9.2,<0.10.0)
Requires-Dist: pydantic-sarif (>=0.1.0,<0.2.0)
Requires-Dist: pyyaml (>=6.0.1,<7.0.0)
Requires-Dist: rich (>=13.7.0,<14.0.0)
Requires-Dist: semgrep (==1.63.0)
Requires-Dist: setuptools (==69.1.1)
Requires-Dist: toolz (>=0.12.0,<0.13.0)
